{
    "andre-navarro-15th-october-2022": {
        "00": {
            "artist": "KAN MIKAMI",
            "title": "Kondo Omae"
        },
        "01": {
            "artist": "YOSHIAKI MASUO",
            "title": "Scarborough Fair"
        },
        "02": {
            "artist": "THE APRYL FOOL",
            "title": "Sunday"
        },
        "03": {
            "artist": "ARAKAWA BAND",
            "title": "The Beast’s Death Theme"
        },
        "04": {
            "artist": "Osamu Kitajima",
            "title": "Say You Will　セイ・ユー・ウィル"
        },
        "05": {
            "artist": "Hiromasa Suzuki",
            "title": "Gentle Wave"
        },
        "06": {
            "artist": "Ann Young, ",
            "title": "What Are You Doing The Rest Of Life?"
        },
        "07": {
            "artist": "Hiromasa Suzuki",
            "title": "Love"
        },
        "08": {
            "artist": "Takeshi Terauchi & Blue Jeans",
            "title": "The Enchanted Sea"
        },
        "09": {
            "artist": "Kimio Mizutani",
            "title": "Sail In The Sky"
        },
        "10": {
            "artist": "ZEROSEN",
            "title": "Asphalt"
        },
        "11": {
            "artist": "MIEKO HIROTA",
            "title": "They Say It’s Wonderful"
        },
        "12": {
            "artist": "Sonia Rosa",
            "title": "Tudo É Você (All Of You)"
        },
        "13": {
            "artist": "Jirō Inagaki & His Soul Media",
            "title": "Back To Rack"
        },
        "14": {
            "artist": "Akira Ishikawa & Count Buffalos",
            "title": "Stone River"
        },
        "15": {
            "artist": "TERUMO AZUMA",
            "title": "Time Limit"
        },
        "16": {
            "artist": "LOVE LIVE LIFE / KOSUKE ICHIHARA",
            "title": "Mr. Sasabe"
        },
        "17": {
            "artist": "AKAI TORI",
            "title": "Awakening"
        },
        "18": {
            "artist": "KUNIHIKO MURAI",
            "title": "Ai To Nikushimi No Ma"
        },
        "19": {
            "artist": "Masahiko Sato",
            "title": "TBSF"
        },
        "20": {
            "artist": "George Hirota",
            "title": "Process Of Cloud"
        },
        "21": {
            "artist": "Hiromasa Suzuki",
            "title": "Gentle Wave"
        },
        "22": {
            "artist": "YUJI OHNO W/ KOJI ISHIZAKA",
            "title": "Manicure"
        },
        "23": {
            "artist": "Sonia Rosa",
            "title": "Te Quero Tanto (I Love You, So)"
        }
    }
}