{
    "ash-lauryn-2nd-september-2022": {
        "00": {
            "artist": "Dam Swindle",
            "title": "High Life (Ash Lauryn Remix)"
        },
        "01": {
            "artist": "CRACKAZAT",
            "title": "Dancecrodile"
        },
        "02": {
            "artist": "SHANNON CHAMBERS",
            "title": "I Remember (Original)"
        },
        "03": {
            "artist": "Earl Jeffers",
            "title": "Black Sunshine (Edit)"
        },
        "04": {
            "artist": "KERRI CHANDLER",
            "title": "See The Light [Lux Frágil] (Long Vocoder Vocal Mix)"
        },
        "05": {
            "artist": "Karizma",
            "title": "Ya Dig (Kaytronik Revision}"
        },
        "06": {
            "artist": "Reggie Dokes",
            "title": "No Plans"
        },
        "07": {
            "artist": "CRACKAZAT",
            "title": "Sarge"
        },
        "08": {
            "artist": "Amp Fiddler",
            "title": "Soul Fly Pt. 2"
        },
        "09": {
            "artist": "ANTHONY NICHOLSON, ",
            "title": "Found"
        },
        "10": {
            "artist": "Black Magic",
            "title": "Freedom (Freedompella)"
        },
        "11": {
            "artist": "Ash Lauryn",
            "title": "Life Is Back"
        }
    }
}